ioStandard/__init__.py
ioStandard/input.py
ioStandard/output.py
ioStandard-0.2.6.dist-info/METADATA
ioStandard-0.2.6.dist-info/WHEEL
ioStandard-0.2.6.dist-info/top_level.txt
ioStandard-0.2.6.dist-info/RECORD
