Metadata-Version: 2.1
Name: ioStandard
Version: 0.2.6
Author: Austin Gilchrist-Thomas
Requires-Dist: pygame
Requires-Dist: datetime
Requires-Dist: tk
